DESCRIPTION
MANIFEST.in
README.rst
setup.py
django_honeypot_signals.egg-info/PKG-INFO
django_honeypot_signals.egg-info/SOURCES.txt
django_honeypot_signals.egg-info/dependency_links.txt
django_honeypot_signals.egg-info/requires.txt
django_honeypot_signals.egg-info/top_level.txt
honeypot_signals/__init__.py
honeypot_signals/models.py
honeypot_signals/templates/honeypot_signals/notification.txt
honeypot_signals/templates/honeypot_signals/notification_subject.txt