Metadata-Version: 1.0
Name: django-honeypot-signals
Version: 0.1.1
Summary: * This app provides a simple signal handler for the App django-admin-honeypot *
